LICENSE
MANIFEST.in
setup.py
deps/hiredis/COPYING
deps/hiredis/async.c
deps/hiredis/async.h
deps/hiredis/dict.c
deps/hiredis/dict.h
deps/hiredis/example-ae.c
deps/hiredis/example-libev.c
deps/hiredis/example-libevent.c
deps/hiredis/example.c
deps/hiredis/fmacros.h
deps/hiredis/hiredis.c
deps/hiredis/hiredis.h
deps/hiredis/net.c
deps/hiredis/net.h
deps/hiredis/sds.c
deps/hiredis/sds.h
deps/hiredis/test.c
deps/hiredis/zmalloc.h
libpy/durable/__init__.py
libpy/durable/engine.py
libpy/durable/interface.py
libpy/durable/lang.py
libpy/durable_rules.egg-info/PKG-INFO
libpy/durable_rules.egg-info/SOURCES.txt
libpy/durable_rules.egg-info/dependency_links.txt
libpy/durable_rules.egg-info/requires.txt
libpy/durable_rules.egg-info/top_level.txt
src/rules/events.c
src/rules/json.c
src/rules/json.h
src/rules/net.c
src/rules/net.h
src/rules/rete.c
src/rules/rete.h
src/rules/rules.h
src/rules/state.c
src/rules/state.h
src/rulespy/rules.c