Metadata-Version: 1.1
Name: durable-rules
Version: 0.32.6
Summary: for real time analytics
Home-page: https://github.com/jruizgit/rules
Author: Jesus Ruiz
Author-email: jr3791@live.com
License: MIT
Keywords: rules_engine rete forward_chaining event_stream state_machine workflow streaming_analytics
Platform: UNKNOWN
Classifier: Operating System :: MacOS
Classifier: Operating System :: POSIX
Classifier: Development Status :: 4 - Beta
Classifier: Intended Audience :: Developers
Classifier: Topic :: Software Development :: Libraries
Classifier: License :: OSI Approved :: MIT License
Classifier: Programming Language :: C
Classifier: Programming Language :: Python :: 2.6
Classifier: Programming Language :: Python :: 2.7
